osustats/__init__.py
osustats/main.py
osustats/helpers/__init__.py
osustats/helpers/mappool_stats.py
osustats/helpers/performance_score.py
osustats/helpers/preprocess.py
osustats/helpers/test.py
osustats-0.0.3.dist-info/LICENSE
osustats-0.0.3.dist-info/METADATA
osustats-0.0.3.dist-info/WHEEL
osustats-0.0.3.dist-info/top_level.txt
osustats-0.0.3.dist-info/RECORD
